{
  "component": "oh-chart-page",
  "config": {
    "label": "Avalon PV: Expected vs Actual",
    "period": "D"
  },
  "props": {
    "parameterGroups": [],
    "parameters": []
  },
  "slots": {
    "dataZoom": [
      {
        "component": "oh-chart-datazoom",
        "config": {
          "type": "inside"
        }
      }
    ],
    "grid": [
      {
        "component": "oh-chart-grid",
        "config": {
          "includeLabels": true
        }
      }
    ],
    "legend": [
      {
        "component": "oh-chart-legend",
        "config": {
          "bottom": 3.0,
          "type": "scroll"
        }
      }
    ],
    "series": [
      {
        "component": "oh-time-series",
        "config": {
          "areaStyle": {
            "opacity": 0.12
          },
          "gridIndex": 0.0,
          "item": "AvalonQ_Miner1_PV_Expected_Watts",
          "name": "Expected PV",
          "type": "line",
          "xAxisIndex": 0.0,
          "yAxisIndex": 0.0
        }
      },
      {
        "component": "oh-time-series",
        "config": {
          "gridIndex": 0.0,
          "item": "AvalonQ_Miner1_PV_Actual_Watts",
          "name": "Actual PV",
          "type": "line",
          "xAxisIndex": 0.0,
          "yAxisIndex": 0.0
        }
      },
      {
        "component": "oh-time-series",
        "config": {
          "gridIndex": 0.0,
          "item": "PV_Power",
          "lineStyle": {
            "type": "dashed"
          },
          "name": "Live PV_Power",
          "type": "line",
          "xAxisIndex": 0.0,
          "yAxisIndex": 0.0
        }
      }
    ],
    "tooltip": [
      {
        "component": "oh-chart-tooltip",
        "config": {
          "confine": true,
          "smartFormatter": true
        }
      }
    ],
    "xAxis": [
      {
        "component": "oh-time-axis",
        "config": {
          "gridIndex": 0.0
        }
      }
    ],
    "yAxis": [
      {
        "component": "oh-value-axis",
        "config": {
          "gridIndex": 0.0,
          "name": "W",
          "scale": true
        }
      }
    ]
  },
  "tags": [
    "avalonq",
    "mining"
  ],
  "timestamp": "Apr 22, 2026, 10:21:34 AM",
  "uid": "Miner_Avalon_PV_Chart"
}
